setup.py
distributions/Binomialdistribution.py
distributions/Gaussiandistribution.py
distributions/Generaldistribution.py
distributions/__init__.py
mve_probability_distributions.egg-info/PKG-INFO
mve_probability_distributions.egg-info/SOURCES.txt
mve_probability_distributions.egg-info/dependency_links.txt
mve_probability_distributions.egg-info/not-zip-safe
mve_probability_distributions.egg-info/top_level.txt